mlflow_registry_mongostore/__init__.py
mlflow_registry_mongostore/_version.py
mlflow_registry_mongostore/models.py
mlflow_registry_mongostore/mongo_store.py
mlflow_registry_mongostore-0.1.11.dist-info/LICENSE
mlflow_registry_mongostore-0.1.11.dist-info/METADATA
mlflow_registry_mongostore-0.1.11.dist-info/WHEEL
mlflow_registry_mongostore-0.1.11.dist-info/entry_points.txt
mlflow_registry_mongostore-0.1.11.dist-info/top_level.txt
mlflow_registry_mongostore-0.1.11.dist-info/RECORD
