Metadata-Version: 2.1
Name: mlflow-registry-mongostore
Version: 0.1.11
Summary: Mlflow plugin to use MongoDB as backend for MLflow Model Registry service
Home-page: 
Author: Rachid Belmeskine
Maintainer-email: rachid.belmeskine@gmail.com
Keywords: mlflow
Classifier: Development Status :: 4 - Beta
Classifier: Intended Audience :: Developers
Classifier: Intended Audience :: Science/Research
Classifier: Operating System :: POSIX :: Linux
Classifier: Environment :: Console
Classifier: License :: OSI Approved :: Apache Software License
Classifier: Programming Language :: Python :: 3
Classifier: Programming Language :: Python :: 3.9
Classifier: Topic :: Software Development :: Libraries
Requires-Python: >=3.8
License-File: LICENSE
Requires-Dist: mongoengine (==0.27.0)
Requires-Dist: mlflow (<3.0.0,>=2.0.0)
